nipanel/__init__.py
nipanel/_convert.py
nipanel/_panel_client.py
nipanel/_panel_value_accessor.py
nipanel/_streamlit_panel.py
nipanel/_streamlit_panel_initializer.py
nipanel/controls/__init__.py
nipanel/controls/_enum_selectbox.py
nipanel/controls/_flag_checkboxes.py
nipanel/converters/__init__.py
nipanel/converters/builtin.py
nipanel/converters/protobuf_types.py
nipanel/streamlit_refresh/__init__.py
nipanel-1.0.0.dist-info/LICENSE
nipanel-1.0.0.dist-info/METADATA
nipanel-1.0.0.dist-info/WHEEL
nipanel-1.0.0.dist-info/RECORD
